MANIFEST.in
NOTES.rst
README.rst
bootstrap.py
dev.cfg.in
doc.txt
edrn.labcas.ui.sublime-project
ops.cfg.in
setup.py
tst.py
docs/HISTORY.txt
docs/INSTALL.txt
docs/LICENSE.txt
etc/base.cfg
etc/cron.cfg
etc/httpd.cfg
etc/misc.cfg
etc/paste.cfg
etc/python.cfg
etc/certs/dev-key.pem
etc/versions/dists.cfg
etc/versions/eggs.cfg
etc/versions/known-good-versions.cfg
src/edrn/__init__.py
src/edrn.labcas.ui.egg-info/PKG-INFO
src/edrn.labcas.ui.egg-info/SOURCES.txt
src/edrn.labcas.ui.egg-info/dependency_links.txt
src/edrn.labcas.ui.egg-info/entry_points.txt
src/edrn.labcas.ui.egg-info/namespace_packages.txt
src/edrn.labcas.ui.egg-info/not-zip-safe
src/edrn.labcas.ui.egg-info/requires.txt
src/edrn.labcas.ui.egg-info/top_level.txt
src/edrn/labcas/__init__.py
src/edrn/labcas/ui/__init__.py
src/edrn/labcas/ui/interfaces.py
src/edrn/labcas/ui/main.py
src/edrn/labcas/ui/settings.py
src/edrn/labcas/ui/utils.py
src/edrn/labcas/ui/vocabularies.py
src/edrn/labcas/ui/resources/__init__.py
src/edrn/labcas/ui/resources/_collection.py
src/edrn/labcas/ui/resources/_collections.py
src/edrn/labcas/ui/resources/_dataset.py
src/edrn/labcas/ui/resources/_file.py
src/edrn/labcas/ui/resources/_management.py
src/edrn/labcas/ui/resources/_root.py
src/edrn/labcas/ui/resources/_upload.py
src/edrn/labcas/ui/static/edrn.css
src/edrn/labcas/ui/static/edrn.png
src/edrn/labcas/ui/static/favicon.ico
src/edrn/labcas/ui/static/mcl.png
src/edrn/labcas/ui/static/mimes.csv
src/edrn/labcas/ui/static/plupload-2.1.9.zip
src/edrn/labcas/ui/static/plupload.full.min.js
src/edrn/labcas/ui/static/pyramid-16x16.png
src/edrn/labcas/ui/static/pyramid.png
src/edrn/labcas/ui/static/theme.css
src/edrn/labcas/ui/static/theme.min.css
src/edrn/labcas/ui/static/custom/metadata_combinations.json
src/edrn/labcas/ui/static/custom/nist-custom.css
src/edrn/labcas/ui/static/custom/nist-custom.js
src/edrn/labcas/ui/templates/about.pt
src/edrn/labcas/ui/templates/accept.pt
src/edrn/labcas/ui/templates/collection.pt
src/edrn/labcas/ui/templates/collections.pt
src/edrn/labcas/ui/templates/dataset.pt
src/edrn/labcas/ui/templates/file.pt
src/edrn/labcas/ui/templates/help.pt
src/edrn/labcas/ui/templates/home.pt
src/edrn/labcas/ui/templates/login.pt
src/edrn/labcas/ui/templates/manage.pt
src/edrn/labcas/ui/templates/master.pt
src/edrn/labcas/ui/templates/metadata.pt
