Metadata-Version: 1.2
Name: edrn.labcas.ui
Version: 1.0.17
Summary: User interface for LabCAS, for EDRN
Home-page: https://github.com/EDRN/edrn.labcas.ui
Author: Sean Kelly
Author-email: sean.kelly@jpl.nasa.gov
Maintainer: Sean Kelly
Maintainer-email: sean.kelly@jpl.nasa.gov
License: ALv2
Keywords: web edrn cancer biomarkers lab laboratory catalog archive
Platform: UNKNOWN
Classifier: Development Status :: 3 - Alpha
Classifier: Environment :: Web Environment
Classifier: Framework :: Pyramid
Classifier: Intended Audience :: Healthcare Industry
Classifier: Intended Audience :: Science/Research
Classifier: License :: OSI Approved :: Apache Software License
Classifier: Operating System :: OS Independent
Classifier: Programming Language :: Python
Classifier: Topic :: Internet :: WWW/HTTP
Classifier: Topic :: Scientific/Engineering :: Bio-Informatics
Classifier: Topic :: Software Development :: Libraries :: Python Modules
